{
  "$schema": "https://emdashcms.com/seed.schema.json",
  "version": "1",
  "meta": {
    "name": "BGI Nexus",
    "description": "BGI Nexus site content and schema",
    "author": "BGI Nexus"
  },
  "settings": {
    "title": "BGI Nexus",
    "tagline": "Beneficial AI"
  },
  "collections": [
    {
      "slug": "pages",
      "label": "Pages",
      "labelSingular": "Page",
      "supports": [
        "drafts",
        "revisions",
        "search",
        "seo"
      ],
      "fields": [
        {
          "slug": "title",
          "label": "Title",
          "type": "string",
          "required": true,
          "searchable": true
        },
        {
          "slug": "content",
          "label": "Content",
          "type": "portableText",
          "searchable": true
        },
        {
          "slug": "sections",
          "label": "Page Sections",
          "type": "json"
        }
      ]
    },
    {
      "slug": "events",
      "label": "Events",
      "labelSingular": "Event",
      "supports": [
        "drafts",
        "revisions",
        "search",
        "seo"
      ],
      "fields": [
        {
          "slug": "title",
          "label": "Title",
          "type": "string",
          "required": true,
          "searchable": true
        },
        {
          "slug": "date_day",
          "label": "Date Day",
          "type": "string"
        },
        {
          "slug": "date_month",
          "label": "Date Month",
          "type": "string"
        },
        {
          "slug": "date_year",
          "label": "Date Year",
          "type": "string"
        },
        {
          "slug": "day_range",
          "label": "Day Range",
          "type": "string"
        },
        {
          "slug": "kind",
          "label": "Kind",
          "type": "string",
          "searchable": true
        },
        {
          "slug": "location",
          "label": "Location",
          "type": "string"
        },
        {
          "slug": "duration",
          "label": "Duration",
          "type": "string"
        },
        {
          "slug": "host",
          "label": "Host",
          "type": "string"
        },
        {
          "slug": "tag",
          "label": "Tag",
          "type": "string"
        },
        {
          "slug": "display_status",
          "label": "Status",
          "type": "string"
        },
        {
          "slug": "body",
          "label": "Body",
          "type": "text",
          "searchable": true
        },
        {
          "slug": "featured",
          "label": "Featured",
          "type": "boolean"
        },
        {
          "slug": "past",
          "label": "Past Event",
          "type": "boolean"
        },
        {
          "slug": "sort_order",
          "label": "Sort Order",
          "type": "integer"
        },
        {
          "slug": "time",
          "label": "Time",
          "type": "string"
        },
        {
          "slug": "link_text",
          "label": "Link Text",
          "type": "string"
        },
        {
          "slug": "link_url",
          "label": "Link URL",
          "type": "string"
        },
        {
          "slug": "lede",
          "label": "Short description",
          "type": "text",
          "searchable": true
        },
        {
          "slug": "programme",
          "label": "Programme",
          "type": "json"
        },
        {
          "slug": "hosts",
          "label": "Hosts & Speakers",
          "type": "json"
        },
        {
          "slug": "themes",
          "label": "Themes",
          "type": "json"
        }
      ]
    },
    {
      "slug": "working_groups",
      "label": "Working Groups",
      "labelSingular": "Working Group",
      "supports": [
        "drafts",
        "revisions",
        "search",
        "seo"
      ],
      "fields": [
        {
          "slug": "name",
          "label": "Name",
          "type": "string",
          "required": true,
          "searchable": true
        },
        {
          "slug": "cycle",
          "label": "Cycle",
          "type": "string"
        },
        {
          "slug": "time",
          "label": "Time",
          "type": "string"
        },
        {
          "slug": "seats",
          "label": "Seats",
          "type": "string"
        },
        {
          "slug": "summary",
          "label": "Summary",
          "type": "text",
          "searchable": true
        },
        {
          "slug": "leads",
          "label": "Leads",
          "type": "json"
        },
        {
          "slug": "topics",
          "label": "Topics",
          "type": "json"
        },
        {
          "slug": "active",
          "label": "Active",
          "type": "boolean"
        },
        {
          "slug": "sort_order",
          "label": "Sort Order",
          "type": "integer"
        }
      ]
    },
    {
      "slug": "projects",
      "label": "Sponsored Projects",
      "labelSingular": "Sponsored Project",
      "supports": [
        "drafts",
        "revisions",
        "search",
        "seo"
      ],
      "fields": [
        {
          "slug": "project_code",
          "label": "Project Code",
          "type": "string"
        },
        {
          "slug": "tag",
          "label": "Tag",
          "type": "string",
          "searchable": true
        },
        {
          "slug": "title",
          "label": "Title",
          "type": "string",
          "required": true,
          "searchable": true
        },
        {
          "slug": "project_byline",
          "label": "Byline",
          "type": "string"
        },
        {
          "slug": "fund",
          "label": "Funding",
          "type": "string"
        },
        {
          "slug": "summary",
          "label": "Summary",
          "type": "text",
          "searchable": true
        },
        {
          "slug": "impact",
          "label": "Impact",
          "type": "text",
          "searchable": true
        },
        {
          "slug": "display_status",
          "label": "Status",
          "type": "string"
        },
        {
          "slug": "round",
          "label": "Round",
          "type": "string"
        },
        {
          "slug": "featured",
          "label": "Featured",
          "type": "boolean"
        },
        {
          "slug": "sort_order",
          "label": "Sort Order",
          "type": "integer"
        },
        {
          "slug": "url",
          "label": "Project URL",
          "type": "string"
        },
        {
          "slug": "tagline",
          "label": "Tagline",
          "type": "text"
        },
        {
          "slug": "story",
          "label": "Story (paragraphs)",
          "type": "json"
        },
        {
          "slug": "team_members",
          "label": "Team Members",
          "type": "json"
        },
        {
          "slug": "timeline",
          "label": "Timeline",
          "type": "json"
        },
        {
          "slug": "impact_stats",
          "label": "Impact Stats",
          "type": "json"
        }
      ]
    },
    {
      "slug": "channels",
      "label": "Channels",
      "labelSingular": "Channel",
      "supports": [
        "drafts",
        "revisions",
        "search"
      ],
      "fields": [
        {
          "slug": "name",
          "label": "Name",
          "type": "string",
          "required": true,
          "searchable": true
        },
        {
          "slug": "handle",
          "label": "Handle",
          "type": "string"
        },
        {
          "slug": "summary",
          "label": "Summary",
          "type": "text",
          "searchable": true
        },
        {
          "slug": "cta",
          "label": "CTA",
          "type": "string"
        },
        {
          "slug": "url",
          "label": "URL",
          "type": "string"
        },
        {
          "slug": "sort_order",
          "label": "Sort Order",
          "type": "integer"
        }
      ]
    },
    {
      "slug": "faqs",
      "label": "FAQs",
      "labelSingular": "FAQ",
      "supports": [
        "drafts",
        "revisions",
        "search"
      ],
      "fields": [
        {
          "slug": "question",
          "label": "Question",
          "type": "string",
          "required": true,
          "searchable": true
        },
        {
          "slug": "answer",
          "label": "Answer",
          "type": "text",
          "searchable": true
        },
        {
          "slug": "sort_order",
          "label": "Sort Order",
          "type": "integer"
        }
      ]
    },
    {
      "slug": "subscribers",
      "label": "Subscribers",
      "labelSingular": "Subscriber",
      "supports": [],
      "fields": [
        {
          "slug": "email",
          "label": "Email",
          "type": "string",
          "required": true
        },
        {
          "slug": "source",
          "label": "Source",
          "type": "string"
        }
      ]
    }
  ],
  "taxonomies": [],
  "menus": [
    {
      "name": "primary",
      "label": "Primary Navigation",
      "items": [
        {
          "type": "custom",
          "label": "About",
          "url": "/about"
        },
        {
          "type": "custom",
          "label": "Events",
          "url": "/events"
        },
        {
          "type": "custom",
          "label": "Working groups",
          "url": "/working-groups"
        },
        {
          "type": "custom",
          "label": "Sponsored projects",
          "url": "/sponsored-projects"
        },
        {
          "type": "custom",
          "label": "Contact",
          "url": "/contact"
        }
      ]
    }
  ],
  "widgetAreas": [],
  "content": {
    "pages": [
      {
        "id": "home",
        "slug": "home",
        "status": "published",
        "data": {
          "title": "BGI Nexus",
          "content": [],
          "sections": {
            "ticker": {
              "items": [
                {
                  "who": "Funded projects",
                  "what": "10 community-selected teams"
                },
                {
                  "who": "Funding deployed",
                  "what": "$500,000 toward beneficial AI"
                },
                {
                  "who": "Countries",
                  "what": "8 represented across the cohort"
                },
                {
                  "who": "Contributors",
                  "what": "953 people in the wider community"
                },
                {
                  "who": "Grant round",
                  "what": "Round 01 funded in 2024"
                },
                {
                  "who": "Community",
                  "what": "events, working groups, and open Q&A"
                }
              ]
            },
            "hero": {
              "eyebrow": "Beneficial AI",
              "headline_line_1": "Where Beneficial AI",
              "headline_line_2": "Gets",
              "headline_emphasis": "Built.",
              "lead": "From idea to impact. We connect builders with funding, expertise, and community to turn beneficial AI projects into reality.",
              "primary_label": "Join a working group",
              "primary_url": "/working-groups",
              "secondary_label": "What is BGI?",
              "secondary_url": "/about"
            },
            "about": {
              "eyebrow": "\u203b BGI Nexus",
              "title": "Community-driven funding",
              "emphasis": "and infrastructure.",
              "body": "BGI Nexus provides community-driven funding and infrastructure for building beneficial AI that serves humanity and our planet.",
              "body_soft": "The initiative connects builders with resources, expertise, and a wider community so promising beneficial AI ideas can move from proposal to real-world impact.",
              "principles": [
                {
                  "word": "Funding",
                  "body": "Community-selected support for teams building beneficial AI projects."
                },
                {
                  "word": "Expertise",
                  "body": "A practical network for mentorship, review, and shared learning."
                },
                {
                  "word": "Community",
                  "body": "Open channels, events, and working groups for people ready to contribute."
                }
              ]
            },
            "pillars": {
              "eyebrow": "How the nexus works",
              "title": "Funding, expertise,",
              "emphasis": "and community.",
              "items": [
                {
                  "num": "01",
                  "title": "Sponsored projects",
                  "count": "10",
                  "label": "funded teams \u00b7 Round 01",
                  "body": "Ten community-selected projects received support to build beneficial AI in health, climate, accessibility, governance, and regenerative systems."
                },
                {
                  "num": "02",
                  "title": "Community events",
                  "count": "03",
                  "label": "public sessions listed",
                  "body": "Community calls and working-group meetups create space for grant progress, updates, open Q&A, and practical collaboration."
                },
                {
                  "num": "03",
                  "title": "Global contributors",
                  "count": "953",
                  "label": "contributors in the network",
                  "body": "BGI Nexus brings together builders, researchers, funders, and community members around beneficial AI that serves humanity and the planet."
                }
              ]
            },
            "working_groups": {
              "intro": "The BGI Nexus working groups are built for people who want to move from conversation to coordinated action, bringing contributors together around practical topics for guiding and governing AGI toward beneficial outcomes."
            },
            "events": {
              "intro": "Monthly community updates, grant progress, open Q&A, and working-group sessions for people building beneficial AI."
            },
            "quote": {
              "lotus": "subtle",
              "eyebrow": "From idea to impact",
              "line_1": "Builders meet funding.",
              "line_2": "Ideas meet expertise.",
              "line_3": "Community turns them into",
              "emphasis": "reality.",
              "side_label": "BGI Nexus",
              "side_body": "Community-driven funding and infrastructure for building beneficial AI that serves humanity and our planet.",
              "cta_label": "Explore funded projects",
              "cta_url": "/sponsored-projects"
            },
            "projects": {
              "intro": "BGI Nexus supports builders creating beneficial AI projects with real-world impact across health, climate resilience, accessibility, governance, agriculture, and ecological knowledge."
            },
            "contact": {
              "title": "Stay",
              "emphasis": "connected.",
              "body": "Get updates on funded projects, grant rounds, and community events, or contact the BGI Nexus team directly."
            }
          }
        }
      },
      {
        "id": "about",
        "slug": "about",
        "status": "published",
        "data": {
          "title": "About",
          "content": [],
          "sections": {
            "hero": {
              "eyebrow": "About BGI Nexus",
              "headline": "Where Beneficial AI",
              "emphasis": "Gets Built."
            },
            "what": {
              "label": "01 \u00b7 General information",
              "title": "What is",
              "emphasis": "BGI Nexus?",
              "body": "BGI Nexus is community-driven funding and infrastructure for building beneficial AI that serves humanity and our planet.",
              "body_soft": "From idea to impact, BGI Nexus connects builders with funding, expertise, and community to turn beneficial AI projects into reality."
            },
            "principles": {
              "label": "02 \u00b7 What the community supports",
              "title": "Beneficial AI",
              "emphasis": "in practice.",
              "body": "The funded cohort shows the breadth of beneficial AI in practice: climate resilience, carbon-credit trust, glucose-data ownership, regenerative biodiversity, accessibility, community governance, agricultural knowledge, and ecological knowledge preservation.",
              "items": [
                {
                  "word": "Humanity",
                  "body": "Projects are selected for practical benefit to people, communities, and public-good systems."
                },
                {
                  "word": "Planet",
                  "body": "Several teams focus on climate resilience, biodiversity, carbon trust, and regenerative ecological knowledge."
                },
                {
                  "word": "Access",
                  "body": "The cohort includes language access, inclusive conferencing, and sign-language translation for underserved communities."
                },
                {
                  "word": "Ownership",
                  "body": "Projects explore community agency, open health data, and democratic decision-making tools."
                },
                {
                  "word": "Impact",
                  "body": "BGI Nexus emphasizes moving from proposals and discussion into funded, measurable work."
                }
              ]
            },
            "spiral": {
              "lotus": "subtle",
              "label": "03 \u00b7 Ecosystem",
              "title": "Part of the",
              "emphasis": "SingularityNET ecosystem.",
              "body": "BGI Nexus is part of the SingularityNET ecosystem, connecting beneficial AI builders with the people and infrastructure needed to move from idea to impact.",
              "body_soft": "The public channels, events, and newsletter help community members follow grant rounds, funded projects, and opportunities to contribute.",
              "primary_label": "View projects",
              "primary_url": "/sponsored-projects",
              "secondary_label": "Stay connected",
              "secondary_url": "/contact"
            },
            "cta": {
              "eyebrow": "Take part",
              "title": "Questions or want",
              "emphasis": "to get involved?",
              "after": "",
              "body": "Get updates on funded projects, grant rounds, and community events, or contact the team directly.",
              "primary_label": "Contact us",
              "primary_url": "/contact",
              "secondary_label": "See events",
              "secondary_url": "/events"
            }
          }
        }
      },
      {
        "id": "events",
        "slug": "events",
        "status": "published",
        "data": {
          "title": "Events",
          "content": [],
          "sections": {
            "hero": {
              "eyebrow": "Events",
              "headline": "Get involved in",
              "emphasis": "BGI Nexus",
              "after": "events.",
              "lead": "Join community calls, grant-progress updates, open Q&A, and working-group sessions focused on beneficial AI."
            },
            "working_groups": {
              "label": "\u203b Working groups",
              "title": "From conversation",
              "emphasis": "to action.",
              "after": "",
              "body": "The BGI Nexus working groups are built for people who want to move from conversation to coordinated action, with practical collaboration around guiding and governing AGI toward beneficial outcomes for humanity."
            },
            "subscribe": {
              "eyebrow": "Stay Connected",
              "title": "Get updates on funded projects,",
              "emphasis": "grant rounds, and community events.",
              "body": "Subscribe for BGI Nexus updates and invitations to future community sessions."
            }
          }
        }
      },
      {
        "id": "working-groups",
        "slug": "working-groups",
        "status": "published",
        "data": {
          "title": "Working groups",
          "content": [],
          "sections": {
            "hero": {
              "eyebrow": "Working groups",
              "headline": "From conversation",
              "emphasis": "to coordinated action.",
              "after": "",
              "lead": "The BGI Nexus working groups are built for people who want to move from conversation to coordinated action around practical topics for beneficial AGI."
            },
            "join": {
              "label": "\u203b What to expect",
              "title": "The kickoff opens",
              "emphasis": "the work.",
              "body": "The kickoff session introduces initial working-group topics, connects contributors with one another, and sets the next phase of collaboration for the BGI Nexus community.",
              "steps": [
                {
                  "num": "01",
                  "title": "Meet the community",
                  "body": "Connect with other members of the BGI Nexus community and learn where people are already contributing."
                },
                {
                  "num": "02",
                  "title": "Explore themes",
                  "body": "Discuss AGI for human flourishing, consciousness, and proactionary versus precautionary approaches to AGI."
                },
                {
                  "num": "03",
                  "title": "Find collaborators",
                  "body": "Match interests, skills, and questions with contributors who want to keep building after the session."
                },
                {
                  "num": "04",
                  "title": "Shape the next phase",
                  "body": "Help shape ongoing collaboration and quarterly meetups around the topics that gather momentum."
                }
              ]
            },
            "sprints": {
              "eyebrow": "Ongoing collaboration",
              "title": "Quarterly",
              "emphasis": "meetups.",
              "body": "Each topic is intended to expand into ongoing collaboration and quarterly meetups, giving the community a recurring rhythm for practical work.",
              "body_soft": "The kickoff session marks the beginning of a series of collaborative working groups focused on guiding and governing AGI toward beneficial outcomes for humanity."
            },
            "directory_note": "Kickoff session \u00b7 02 Dec 2025"
          }
        }
      },
      {
        "id": "sponsored-projects",
        "slug": "sponsored-projects",
        "status": "published",
        "data": {
          "title": "Sponsored projects",
          "content": [],
          "sections": {
            "hero": {
              "eyebrow": "Sponsored projects",
              "headline": "Funded beneficial AI",
              "emphasis": "in practice.",
              "lead": "BGI Nexus funded ten projects building beneficial AI across health, climate, accessibility, governance, agriculture, and ecological knowledge."
            },
            "round": {
              "label": "\u203b Round 01 \u00b7 2024",
              "title": "Community-selected",
              "emphasis": "projects,",
              "after": "real-world impact.",
              "body": "The BGI Nexus community came together to fund the first wave of beneficial AI projects, deploying support to ten teams working on practical public-good applications.",
              "body_soft": "From social and environmental solutions to safer and more compassionate AI systems, each project contributes to a more democratic ecosystem of innovation that benefits people, societies, and the biosphere."
            },
            "funding": {
              "eyebrow": "\u203b Funding model",
              "title": "Community-driven.",
              "emphasis": "Impact-focused.",
              "body": "Get updates on funded projects, grant rounds, and community events through the BGI Nexus newsletter and public channels."
            }
          }
        }
      },
      {
        "id": "contact",
        "slug": "contact",
        "status": "published",
        "data": {
          "title": "Contact",
          "content": [],
          "sections": {
            "hero": {
              "eyebrow": "Contact",
              "headline": "Get in",
              "emphasis": "Touch.",
              "lead": "Questions or want to get involved? Contact BGI Nexus directly or follow the community channels for updates."
            },
            "registration": {
              "label": "\u203b Stay Connected",
              "title": "Get updates on funded projects,",
              "emphasis": "grant rounds, and community events.",
              "body": "Subscribe for BGI Nexus updates, community events, and future grant-round announcements.",
              "connect_options": [
                "Contributor",
                "Builder",
                "Researcher",
                "Funder",
                "Curious"
              ],
              "update_options": [
                "Working groups",
                "Events",
                "Projects",
                "General"
              ]
            },
            "faq_intro": {
              "label": "\u203b Quick links",
              "title": "Before you",
              "emphasis": "write.",
              "body": "The public site highlights the newsletter, direct email, and social channels as the best ways to stay connected."
            }
          }
        }
      }
    ],
    "events": [
      {
        "id": "event-agi-human-flourishing-weekly",
        "slug": "bgi-nexus-community-call-february-2026",
        "status": "published",
        "data": {
          "title": "BGI Nexus Community Call",
          "date_day": "10",
          "date_month": "FEB",
          "date_year": "2026",
          "kind": "Community call",
          "location": "Online",
          "duration": "Monthly call",
          "time": "12:00 UTC",
          "host": "BGI Nexus",
          "tag": "Event",
          "display_status": "Recording available",
          "body": "Monthly community updates, grant progress, and open Q&A.",
          "featured": false,
          "past": true,
          "link_text": "View recording",
          "link_url": "",
          "sort_order": 10
        }
      },
      {
        "id": "event-healthy-human-ai-ecosystems",
        "slug": "bgi-nexus-community-call-january-2026",
        "status": "published",
        "data": {
          "title": "BGI Nexus Community Call",
          "date_day": "13",
          "date_month": "JAN",
          "date_year": "2026",
          "kind": "Community call",
          "location": "Online",
          "duration": "Monthly call",
          "time": "12:00 UTC",
          "host": "BGI Nexus",
          "tag": "Event",
          "display_status": "Recording available",
          "body": "Monthly community updates, grant progress, and open Q&A.",
          "featured": false,
          "past": true,
          "link_text": "View recording",
          "link_url": "",
          "sort_order": 20
        }
      },
      {
        "id": "event-pluralistic-value-systems-fortnightly",
        "slug": "bgi-nexus-working-groups-kickoff-session",
        "status": "published",
        "data": {
          "title": "BGI Nexus Working Groups - The Kickoff Session",
          "date_day": "02",
          "date_month": "DEC",
          "date_year": "2025",
          "kind": "Working group kickoff",
          "location": "Zoom (link sent to registered attendees)",
          "duration": "2 hours",
          "time": "19:00 UTC",
          "host": "BGI Nexus community",
          "tag": "Working groups",
          "display_status": "Recording available",
          "body": "Join us for the first working-group meetup in the BGI Nexus community. This kickoff session launches a series of practical, collaborative working groups focused on guiding and governing AGI toward beneficial outcomes for humanity.",
          "featured": false,
          "past": true,
          "link_text": "View recording",
          "link_url": "https://mailchi.mp/singularitynet.io/x4xss53zgt",
          "sort_order": 30
        }
      },
      {
        "id": "event-bgi-mini-hackathon",
        "slug": "bgi-mini-hackathon",
        "status": "draft",
        "data": {
          "title": "Archived placeholder",
          "date_day": "01",
          "date_month": "JAN",
          "date_year": "2026",
          "kind": "Archived",
          "location": "Online",
          "display_status": "Archived",
          "past": true,
          "sort_order": 100
        }
      },
      {
        "id": "event-past-agi-human-flourishing",
        "slug": "past-agi-human-flourishing",
        "status": "draft",
        "data": {
          "title": "Archived placeholder",
          "date_day": "01",
          "date_month": "JAN",
          "date_year": "2026",
          "kind": "Archived",
          "location": "Online",
          "display_status": "Archived",
          "past": true,
          "sort_order": 101
        }
      },
      {
        "id": "event-past-spirals-opening",
        "slug": "past-spirals-opening",
        "status": "draft",
        "data": {
          "title": "Archived placeholder",
          "date_day": "01",
          "date_month": "JAN",
          "date_year": "2026",
          "kind": "Archived",
          "location": "Online",
          "display_status": "Archived",
          "past": true,
          "sort_order": 102
        }
      },
      {
        "id": "event-past-multi-agent-alignment",
        "slug": "past-multi-agent-alignment",
        "status": "draft",
        "data": {
          "title": "Archived placeholder",
          "date_day": "01",
          "date_month": "JAN",
          "date_year": "2026",
          "kind": "Archived",
          "location": "Online",
          "display_status": "Archived",
          "past": true,
          "sort_order": 103
        }
      }
    ],
    "working_groups": [
      {
        "id": "wg-flourishing",
        "slug": "agi-for-human-flourishing",
        "status": "published",
        "data": {
          "name": "AGI for Human Flourishing / Nurturing & Governing AGI",
          "cycle": "Initial working-group topic",
          "time": "Kickoff session and quarterly meetups",
          "seats": "Open to contributors",
          "summary": "A working group topic focused on guiding and governing AGI toward beneficial outcomes for humanity.",
          "leads": [
            "BGI Nexus community"
          ],
          "topics": [
            "Human flourishing",
            "AGI governance",
            "Beneficial outcomes"
          ],
          "active": true,
          "sort_order": 10
        }
      },
      {
        "id": "wg-pluralistic",
        "slug": "the-consciousness-revolution",
        "status": "published",
        "data": {
          "name": "The Consciousness Revolution",
          "cycle": "Initial working-group topic",
          "time": "Kickoff session and quarterly meetups",
          "seats": "Open to contributors",
          "summary": "A working group topic for exploring consciousness, human meaning, and the role of AGI in supporting flourishing life.",
          "leads": [
            "BGI Nexus community"
          ],
          "topics": [
            "Consciousness",
            "Human meaning",
            "Flourishing life"
          ],
          "active": true,
          "sort_order": 20
        }
      },
      {
        "id": "wg-political",
        "slug": "proactionary-vs-precautionary-agi",
        "status": "published",
        "data": {
          "name": "Proactionary vs Precautionary Approaches to AGI",
          "cycle": "Initial working-group topic",
          "time": "Kickoff session and quarterly meetups",
          "seats": "Open to contributors",
          "summary": "A working group topic for comparing proactionary and precautionary approaches to AGI development, risk, and governance.",
          "leads": [
            "BGI Nexus community"
          ],
          "topics": [
            "AGI approaches",
            "Risk and governance",
            "Coordination"
          ],
          "active": true,
          "sort_order": 30
        }
      },
      {
        "id": "wg-multiagent",
        "slug": "wg-multiagent",
        "status": "draft",
        "data": {
          "name": "Archived working-group placeholder",
          "cycle": "Archived",
          "time": "Archived",
          "seats": "Archived",
          "summary": "Archived during synchronization with the public BGI Nexus site.",
          "leads": [
            "BGI Nexus"
          ],
          "topics": [
            "Archived"
          ],
          "active": false,
          "sort_order": 100
        }
      },
      {
        "id": "wg-offernet",
        "slug": "wg-offernet",
        "status": "draft",
        "data": {
          "name": "Archived working-group placeholder",
          "cycle": "Archived",
          "time": "Archived",
          "seats": "Archived",
          "summary": "Archived during synchronization with the public BGI Nexus site.",
          "leads": [
            "BGI Nexus"
          ],
          "topics": [
            "Archived"
          ],
          "active": false,
          "sort_order": 101
        }
      },
      {
        "id": "wg-omni",
        "slug": "wg-omni",
        "status": "draft",
        "data": {
          "name": "Archived working-group placeholder",
          "cycle": "Archived",
          "time": "Archived",
          "seats": "Archived",
          "summary": "Archived during synchronization with the public BGI Nexus site.",
          "leads": [
            "BGI Nexus"
          ],
          "topics": [
            "Archived"
          ],
          "active": false,
          "sort_order": 102
        }
      }
    ],
    "projects": [
      {
        "id": "project-productivity-eeg-ai-agents",
        "slug": "productivity-eeg-ai-agents",
        "status": "published",
        "data": {
          "project_code": "P-01",
          "tag": "Health",
          "title": "Productivity EEG-AI Agents",
          "project_byline": "BGI Team",
          "fund": "$50,000",
          "summary": "Brain-signal-powered productivity system using EEG data and AI for cognitive enhancement.",
          "impact": "Achieved 15% average productivity improvement in 200+ users through EEG-AI integration.",
          "display_status": "Active build",
          "round": "Round 01 \u00b7 2024",
          "featured": true,
          "url": "https://productivity-eeg.ai",
          "sort_order": 10
        }
      },
      {
        "id": "project-acropolis-os",
        "slug": "acropolis-os",
        "status": "published",
        "data": {
          "project_code": "P-02",
          "tag": "Governance",
          "title": "Acropolis OS - Autonomous Community AGI",
          "project_byline": "BGI Team",
          "fund": "$50,000",
          "summary": "Operating system using AGI for democratic decision-making in autonomous communities.",
          "impact": "Supporting governance for 8 autonomous communities with AI-driven decision tools.",
          "display_status": "Active build",
          "round": "Round 01 \u00b7 2024",
          "featured": false,
          "url": "https://acropolisos.org",
          "sort_order": 20
        }
      },
      {
        "id": "project-nigerguard",
        "slug": "nigerguard",
        "status": "published",
        "data": {
          "project_code": "P-03",
          "tag": "Climate",
          "title": "NigerGuard: AI Climate Resilience-Vulnerable States",
          "project_byline": "BGI Team",
          "fund": "$46,000",
          "summary": "AI-powered climate resilience platform for vulnerable regions with early warning systems.",
          "impact": "Protecting 250,000+ people across vulnerable regions with early warning systems.",
          "display_status": "Active build",
          "round": "Round 01 \u00b7 2024",
          "featured": false,
          "url": "https://nigerguard.org",
          "sort_order": 30
        }
      },
      {
        "id": "project-aurora",
        "slug": "aurora",
        "status": "published",
        "data": {
          "project_code": "P-04",
          "tag": "Climate",
          "title": "AURORA: Decentralised AI for Carbon Credit Trust",
          "project_byline": "BGI Team",
          "fund": "$50,000",
          "summary": "Decentralized AI platform bringing transparency to carbon credit markets through automated verification.",
          "impact": "Verified $2.3M in carbon credits with 99.2% accuracy using AI validation.",
          "display_status": "Active build",
          "round": "Round 01 \u00b7 2024",
          "featured": false,
          "url": "https://aurora-carbon.org",
          "sort_order": 40
        }
      },
      {
        "id": "project-glucosedao",
        "slug": "glucosedao",
        "status": "published",
        "data": {
          "project_code": "P-05",
          "tag": "Health",
          "title": "GlucoseDAO",
          "project_byline": "BGI Team",
          "fund": "$50,000",
          "summary": "Open health platform democratizing glucose data ownership while advancing diabetes research.",
          "impact": "1,200+ users contributing anonymized glucose data for diabetes research.",
          "display_status": "Active build",
          "round": "Round 01 \u00b7 2024",
          "featured": false,
          "url": "https://glucosedao.org",
          "sort_order": 50
        }
      },
      {
        "id": "project-bionexus-gaia",
        "slug": "bionexus-gaia",
        "status": "published",
        "data": {
          "project_code": "P-06",
          "tag": "Ecology",
          "title": "BIONEXUS GAIA: AI for Regenerative Biodiversity",
          "project_byline": "BGI Team",
          "fund": "$50,000",
          "summary": "Advanced AI system for biodiversity regeneration and ecosystem recovery monitoring.",
          "impact": "Monitoring 50+ restoration sites across 8 countries with AI-driven insights.",
          "display_status": "Active build",
          "round": "Round 01 \u00b7 2024",
          "featured": false,
          "url": "https://bionexusgaia.org",
          "sort_order": 60
        }
      },
      {
        "id": "project-lovelock-living-libraries",
        "slug": "lovelock-living-libraries",
        "status": "published",
        "data": {
          "project_code": "P-07",
          "tag": "Ecology",
          "title": "Project Lovelock - Living Libraries Network",
          "project_byline": "BGI Team",
          "fund": "$48,888",
          "summary": "Decentralized ecological knowledge repositories preserving indigenous wisdom and scientific biodiversity data.",
          "impact": "Preserving knowledge from 30+ indigenous communities and creating biodiversity databases.",
          "display_status": "Active build",
          "round": "Round 01 \u00b7 2024",
          "featured": false,
          "url": "https://projectlovelock.org",
          "sort_order": 70
        }
      },
      {
        "id": "project-sign-language-translator-ai",
        "slug": "sign-language-translator-ai",
        "status": "published",
        "data": {
          "project_code": "P-08",
          "tag": "Access",
          "title": "Sign Language Translator AI (SLTA)",
          "project_byline": "BGI Team",
          "fund": "$50,000",
          "summary": "AI-powered sign language translation system bridging communication gaps through real-time visual recognition.",
          "impact": "Achieved 95% accuracy rate across 15 sign language variants, serving deaf communities globally.",
          "display_status": "Active build",
          "round": "Round 01 \u00b7 2024",
          "featured": false,
          "url": "https://slta.ai",
          "sort_order": 80
        }
      },
      {
        "id": "project-think-inclusion-conferencing",
        "slug": "think-inclusion-conferencing",
        "status": "published",
        "data": {
          "project_code": "P-09",
          "tag": "Access",
          "title": "Think Inclusion Conferencing App",
          "project_byline": "BGI Team",
          "fund": "$45,000",
          "summary": "Inclusive design conferencing platform ensuring global events are accessible to people with disabilities.",
          "impact": "Hosted 25+ accessible events reaching 10,000+ participants worldwide.",
          "display_status": "Active build",
          "round": "Round 01 \u00b7 2024",
          "featured": false,
          "url": "https://thinkinclusion.app",
          "sort_order": 90
        }
      },
      {
        "id": "project-farmlingua",
        "slug": "farmlingua",
        "status": "published",
        "data": {
          "project_code": "P-10",
          "tag": "Language",
          "title": "Farmlingua",
          "project_byline": "BGI Team",
          "fund": "$45,000",
          "summary": "Multilingual AI platform for smallholder farmers, breaking down language barriers in agricultural knowledge sharing.",
          "impact": "Supporting 500+ smallholder farmers across 12 countries with localized agricultural guidance.",
          "display_status": "Active build",
          "round": "Round 01 \u00b7 2024",
          "featured": false,
          "url": "https://farmlingua.org",
          "sort_order": 100
        }
      }
    ],
    "channels": [
      {
        "id": "channel-discord",
        "slug": "discord",
        "status": "published",
        "data": {
          "name": "Discord",
          "handle": "bgicollective.singularitynet.io/Discord",
          "summary": "Join the BGI Nexus community conversation and stay close to funded projects, grant rounds, and community events.",
          "cta": "Join Discord",
          "url": "https://bgicollective.singularitynet.io/Discord",
          "sort_order": 10
        }
      },
      {
        "id": "channel-telegram",
        "slug": "telegram",
        "status": "published",
        "data": {
          "name": "Telegram",
          "handle": "t.me/+8PKlTLYeQac4ZWVh",
          "summary": "Follow announcements and updates from the BGI Nexus community.",
          "cta": "Open Telegram",
          "url": "https://t.me/+8PKlTLYeQac4ZWVh",
          "sort_order": 20
        }
      },
      {
        "id": "channel-linkedin",
        "slug": "linkedin",
        "status": "published",
        "data": {
          "name": "LinkedIn",
          "handle": "linkedin.com/groups/12964136",
          "summary": "Connect with the wider BGI Nexus network across partners, contributors, funders, and organizations.",
          "cta": "View group",
          "url": "https://www.linkedin.com/groups/12964136/",
          "sort_order": 30
        }
      }
    ],
    "faqs": [
      {
        "id": "faq-technical-background",
        "slug": "stay-connected",
        "status": "published",
        "data": {
          "question": "How do I stay connected?",
          "answer": "Subscribe to get updates on funded projects, grant rounds, and community events.",
          "sort_order": 10
        }
      },
      {
        "id": "faq-next-funding-round",
        "slug": "get-in-touch",
        "status": "published",
        "data": {
          "question": "How do I get in touch?",
          "answer": "Email bginexus@singularitynet.io with questions or to get involved.",
          "sort_order": 20
        }
      },
      {
        "id": "faq-partner",
        "slug": "follow-bgi-nexus",
        "status": "published",
        "data": {
          "question": "Where can I follow BGI Nexus?",
          "answer": "BGI Nexus is on Discord, Telegram, and LinkedIn through the public community links listed on this page.",
          "sort_order": 30
        }
      },
      {
        "id": "faq-start-working-group",
        "slug": "singularitynet-ecosystem",
        "status": "published",
        "data": {
          "question": "Is BGI Nexus part of SingularityNET?",
          "answer": "Yes. The public site describes BGI Nexus as part of the SingularityNET ecosystem.",
          "sort_order": 40
        }
      },
      {
        "id": "faq-recorded",
        "slug": "funded-projects",
        "status": "published",
        "data": {
          "question": "Where can I learn about funded projects?",
          "answer": "The sponsored projects page lists the funded BGI Nexus cohort and links to each project site.",
          "sort_order": 50
        }
      }
    ]
  }
}